config/__init__.py
config/file.py
config/sql.py
mih_config-1.0.0.dist-info/METADATA
mih_config-1.0.0.dist-info/WHEEL
mih_config-1.0.0.dist-info/namespace_packages.txt
mih_config-1.0.0.dist-info/top_level.txt
mih_config-1.0.0.dist-info/zip-safe
mih_config-1.0.0.dist-info/RECORD
