Metadata-Version: 2.1
Name: mih-config
Version: 1.0.0
Summary: UNKNOWN
Home-page: UNKNOWN
Author: MIH
Author-email: UNKNOWN
License: UNKNOWN
Platform: UNKNOWN
Classifier: Development Status :: 3 - Alpha
Classifier: Programming Language :: Python
Requires-Dist: mih-constant
